<!DOCTYPE PATCH  SYSTEM "http://vvvv.org/versions/vvvv45beta33.7.dtd" >
   <PATCH nodename="D:\Copy\Projects\CatGui0.5\Subs\TitleBar.v4p" systemname="TitleBar" filename="D:\Copy\Projects\CatGui0.5\Subs\TitleBar.v4p">
   <NODE systemname="Text (DX11.Layer)" filename="%VVVV%\packs\dx11\nodes\plugins\VVVV.DX11.Nodes.Text.dll" nodename="Text (DX11.Layer)" componentmode="Hidden" id="0">
   <BOUNDS type="Node" left="1500" top="1500" width="100" height="100">
   </BOUNDS>
   <PIN pinname="Layer" visible="1">
   </PIN>
   </NODE>
   <NODE id="1" systemname="IOBox (Node)" componentmode="InABox" nodename="IOBox (Node)">
   <PIN pinname="Descriptive Name" slicecount="1" values="Layer">
   </PIN>
   <BOUNDS type="Box" left="1500" top="2100" width="750" height="240">
   </BOUNDS>
   <BOUNDS type="Node" left="1500" top="2100" width="750" height="240">
   </BOUNDS>
   </NODE>
   <LINK srcnodeid="0" srcpinname="Layer" dstnodeid="1" dstpinname="Input Node">
   </LINK>
   <BOUNDS type="Window" left="-1" top="-1" width="3100" height="3100">
   </BOUNDS>
   <PACK Name="addonpack" Version="33.7.0">
   </PACK>
   </PATCH>